[
    {
        "listened_at": "2022-05-23T20:28:34",
        "track_name": "Yeah! (feat. Lil Jon & Ludacris)",
        "artist_name": "Usher, Lil Jon, Ludacris",
        "release_name": "Confessions (Expanded Edition)",
        "recording_mbid": null,
        "artist_mbids": [],
        "release_mbid": null,
        "tags": [],
        "release_group_mbid": [],
        "work_mbids": [],
        "tracknumber": 2,
        "spotify_id": "https://open.spotify.com/track/5rb9QrpfcKFHM1EUbSIurX",
        "listening_from": "spotify",
        "isrc": "USAR10301423",
        "additional_info": {
            "artist_msid": "a89da5dc-811a-48ee-9f56-54f76eb1143a",
            "artist_names": [
                "Usher",
                "Lil Jon",
                "Ludacris"
            ],
            "discnumber": 1,
            "duration_ms": 250373,
            "isrc": "USAR10301423",
            "listening_from": "spotify",
            "recording_msid": "4896a277-492c-4866-b726-76fc1bc9922e",
            "release_artist_name": "Usher",
            "release_artist_names": [
                "Usher"
            ],
            "release_msid": "a1a8e712-1d21-403a-ac96-9a24c912c764",
            "spotify_album_artist_ids": [
                "https://open.spotify.com/artist/23zg3TcAtWQy7J6upgbUnj"
            ],
            "spotify_album_id": "https://open.spotify.com/album/1RM6MGv6bcl6NrAG8PGoZk",
            "spotify_artist_ids": [
                "https://open.spotify.com/artist/23zg3TcAtWQy7J6upgbUnj",
                "https://open.spotify.com/artist/7sfl4Xt5KmfyDs2T3SVSMK",
                "https://open.spotify.com/artist/3ipn9JLAPI5GUEo4y4jcoi"
            ],
            "spotify_id": "https://open.spotify.com/track/5rb9QrpfcKFHM1EUbSIurX",
            "tracknumber": 2
        },
        "username": null
    },
    {
        "listened_at": "2022-05-18T01:59:48",
        "track_name": "Come Through and Chill (feat. J. Cole & Salaam Remi)",
        "artist_name": "Miguel, J. Cole, Salaam Remi",
        "release_name": "War & Leisure",
        "recording_mbid": null,
        "artist_mbids": [],
        "release_mbid": null,
        "tags": [],
        "release_group_mbid": [],
        "work_mbids": [],
        "tracknumber": 10,
        "spotify_id": "https://open.spotify.com/track/1m8WpLYXEiNVZchsWEcCSy",
        "listening_from": "spotify",
        "isrc": "USRC11702833",
        "additional_info": {
            "artist_msid": "c2af6b6c-b64b-4038-acdb-2409fbc644b6",
            "artist_names": [
                "Miguel",
                "J. Cole",
                "Salaam Remi"
            ],
            "discnumber": 1,
            "duration_ms": 322000,
            "isrc": "USRC11702833",
            "listening_from": "spotify",
            "recording_msid": "79cacd27-38a3-4ef4-85d0-161aa5407249",
            "release_artist_name": "Miguel",
            "release_artist_names": [
                "Miguel"
            ],
            "release_msid": "0e3f6ff6-8938-4895-8686-4cc29477772f",
            "spotify_album_artist_ids": [
                "https://open.spotify.com/artist/360IAlyVv4PCEVjgyMZrxK"
            ],
            "spotify_album_id": "https://open.spotify.com/album/05LEST8E8mkEIl2LRfUkcI",
            "spotify_artist_ids": [
                "https://open.spotify.com/artist/360IAlyVv4PCEVjgyMZrxK",
                "https://open.spotify.com/artist/6l3HvQ5sa6mXTsMTB19rO5",
                "https://open.spotify.com/artist/0rlS0SzVFk8BoiAW0fGBbN"
            ],
            "spotify_id": "https://open.spotify.com/track/1m8WpLYXEiNVZchsWEcCSy",
            "tracknumber": 10
        },
        "username": null
    },
    {
        "listened_at": "2022-05-16T22:46:18",
        "track_name": "Me Gustas Tu",
        "artist_name": "Manu Chao",
        "release_name": "Pr\u00f3xima Estaci\u00f3n: Esperanza",
        "recording_mbid": null,
        "artist_mbids": [],
        "release_mbid": null,
        "tags": [],
        "release_group_mbid": [],
        "work_mbids": [],
        "tracknumber": 6,
        "spotify_id": "https://open.spotify.com/track/6b37xrsNCWYIUphFBazqD6",
        "listening_from": "spotify",
        "isrc": "FR84R0000004",
        "additional_info": {
            "artist_msid": "07289f5a-657e-4ce8-bf3c-bb6b232c9ac5",
            "artist_names": [
                "Manu Chao"
            ],
            "discnumber": 1,
            "duration_ms": 239986,
            "isrc": "FR84R0000004",
            "listening_from": "spotify",
            "recording_msid": "c9c475a3-4e17-42ce-be5d-a58dbdc28894",
            "release_artist_name": "Manu Chao",
            "release_artist_names": [
                "Manu Chao"
            ],
            "release_msid": "00d2c097-a890-4eec-b9e1-82fd96ce3166",
            "spotify_album_artist_ids": [
                "https://open.spotify.com/artist/6wH6iStAh4KIaWfuhf0NYM"
            ],
            "spotify_album_id": "https://open.spotify.com/album/4t1LLdXiWTfoywqricztFo",
            "spotify_artist_ids": [
                "https://open.spotify.com/artist/6wH6iStAh4KIaWfuhf0NYM"
            ],
            "spotify_id": "https://open.spotify.com/track/6b37xrsNCWYIUphFBazqD6",
            "tracknumber": 6
        },
        "username": null
    }
]